Metadata-Version: 2.1
Name: holiday_predictor
Version: 1.0.1
Summary: 一个预测中国的假期安排的小工具
Home-page: https://github.com/azaz-az/holiday-predictor
Author: azaz-az
Author-email: a233d@outlook.com
Keywords: holiday,predictor,holiday_predictor,chinese_holiday
Classifier: Programming Language :: Python :: 3
Classifier: License :: OSI Approved :: GNU General Public License v3 (GPLv3)
Classifier: Operating System :: OS Independent
Requires-Python: >=3.6
License-File: LICENSE
Requires-Dist: zhdate
